sqlflow/__init__.py
sqlflow/__main__.py
sqlflow/_version.py
sqlflow/client.py
sqlflow/compound_message.py
sqlflow/env_expand.py
sqlflow/magic.py
sqlflow/rows.py
sqlflow/proto/sqlflow_pb2.py
sqlflow/proto/sqlflow_pb2_grpc.py
sqlflow-0.15.0.dist-info/LICENSE
sqlflow-0.15.0.dist-info/METADATA
sqlflow-0.15.0.dist-info/WHEEL
sqlflow-0.15.0.dist-info/entry_points.txt
sqlflow-0.15.0.dist-info/top_level.txt
sqlflow-0.15.0.dist-info/RECORD
