Metadata-Version: 2.1
Name: sqlflow
Version: 0.15.0
Summary: SQLFlow client library for Python.
Home-page: https://github.com/sql-machine-learning/sqlflow
Author: Kuisong Tong
Author-email: kuisong.tong@gmail.com
License: Apache License 2.0
Platform: UNKNOWN
Classifier: License :: OSI Approved :: Apache Software License
Classifier: Programming Language :: Python
Classifier: Programming Language :: Python :: 3 :: Only
Classifier: Programming Language :: Python :: 3.5
Classifier: Programming Language :: Python :: 3.6
Classifier: Programming Language :: Python :: 3.7
Classifier: Programming Language :: Python :: Implementation :: CPython
Classifier: Programming Language :: Python :: Implementation :: PyPy
Requires-Python: >=3.5.0
Requires-Dist: protobuf (==3.7.1)
Requires-Dist: grpcio (<2,>=1.17)
Requires-Dist: ipython (==7.9)
Requires-Dist: pandas
